{
  "epicenter_lat": "24.41",
  "epicenter_lon": "120.86",
  "magnitude": "3.1",
  "max_intensity": "2",
  "locations": [
    {
      "latitude": "24.4144",
      "longitude": "120.7697",
      "county": "苗栗縣",
      "intensity": "2",
      "location_name": "三義"
    },
    {
      "latitude": "24.3465",
      "longitude": "120.7809",
      "county": "苗栗縣",
      "intensity": "1",
      "location_name": "鯉魚潭"
    },
    {
      "latitude": "24.6836",
      "longitude": "120.8703",
      "county": "苗栗縣",
      "intensity": "1",
      "location_name": "竹南"
    },
    {
      "latitude": "24.5374",
      "longitude": "120.7909",
      "county": "苗栗縣",
      "intensity": "1",
      "location_name": "苗栗市"
    },
    {
      "latitude": "24.2777",
      "longitude": "120.9458",
      "county": "臺中市",
      "intensity": "2",
      "location_name": "烏石坑"
    }
  ]
}