{
    "event_id": "2023_043",
    "timestamp": "2023-06-23T02:45:30",
    "epicenter_latitude": 24.55,
    "epicenter_longitude": 121.67,
    "depth_km": 59.3,
    "magnitude": 4.8,
    "max_intensity_observed": 2,
    "source_type": "detailed_station",
    "affected_locations": [
        {
            "location_name": "木柵",
            "latitude": 24.98,
            "longitude": 121.59,
            "county": "臺北市",
            "intensity": 1,
            "station_code": "TWA",
            "distance_km": 47.67,
            "pga_v": 0.46,
            "pga_ns": 1.03,
            "pga_ew": 0.83,
            "pgv_v": 0.02,
            "pgv_ns": 0.03,
            "pgv_ew": 0.04
        },
        {
            "location_name": "梨山",
            "latitude": 24.25,
            "longitude": 121.24,
            "county": "臺中市",
            "intensity": 2,
            "station_code": "FUSS",
            "distance_km": 55.13,
            "pga_v": 0.96,
            "pga_ns": 2.41,
            "pga_ew": 3.07,
            "pgv_v": 0.06,
            "pgv_ns": 0.1,
            "pgv_ew": 0.15
        },
        {
            "location_name": "臺北市",
            "latitude": 25.04,
            "longitude": 121.51,
            "county": "臺北市",
            "intensity": 1,
            "station_code": "TAP",
            "distance_km": 55.93,
            "pga_v": 0.78,
            "pga_ns": 1.28,
            "pga_ew": 1.01,
            "pgv_v": 0.03,
            "pgv_ns": 0.07,
            "pgv_ew": 0.04
        },
        {
            "location_name": "德基",
            "latitude": 24.25,
            "longitude": 121.16,
            "county": "臺中市",
            "intensity": 2,
            "station_code": "TWT",
            "distance_km": 61.79,
            "pga_v": 1.6,
            "pga_ns": 4.06,
            "pga_ew": 1.84,
            "pgv_v": 0.06,
            "pgv_ns": 0.18,
            "pgv_ew": 0.08
        },
        {
            "location_name": "烏石坑",
            "latitude": 24.28,
            "longitude": 120.95,
            "county": "臺中市",
            "intensity": 1,
            "station_code": "WHP",
            "distance_km": 79.77,
            "pga_v": 0.82,
            "pga_ns": 0.94,
            "pga_ew": 0.73,
            "pgv_v": 0.03,
            "pgv_ns": 0.08,
            "pgv_ew": 0.07
        }
    ]
}