{
  "earthquake_id": "040",
  "timestamp": "2021-06-11T15:33:26",
  "latitude": 23.89,
  "longitude": 121.53,
  "depth_km": 10.6,
  "magnitude": 5.4,
  "stations": [
    {
      "Stacode": "FUSS",
      "Staname": "梨山",
      "Stalon": 121.24,
      "Stalat": 24.25,
      "Dist": 49.12,
      "AZ": 143.67,
      "PGA(V)": 2.37,
      "PGA(NS)": 5.85,
      "PGA(EW)": 5.33,
      "PGV(V)": 0.14,
      "PGV(NS)": 0.3,
      "PGV(EW)": 0.23,
      "Int": 2,
      "PGA(SUM)": 6.3,
      "PGV(SUM)": 0.31,
      "City": "臺中市"
    },
    {
      "Stacode": "TWT",
      "Staname": "德基",
      "Stalon": 121.16,
      "Stalat": 24.25,
      "Dist": 54.61,
      "AZ": 136.75,
      "PGA(V)": 1.38,
      "PGA(NS)": 5.36,
      "PGA(EW)": 2.55,
      "PGV(V)": 0.09,
      "PGV(NS)": 0.23,
      "PGV(EW)": 0.16,
      "Int": 2,
      "PGA(SUM)": 5.33,
      "PGV(SUM)": 0.24,
      "City": "臺中市"
    },
    {
      "Stacode": "WHP",
      "Staname": "烏石坑",
      "Stalon": 120.95,
      "Stalat": 24.28,
      "Dist": 73.27,
      "AZ": 125.84,
      "PGA(V)": 0.91,
      "PGA(NS)": 1.24,
      "PGA(EW)": 1.36,
      "PGV(V)": 0.09,
      "PGV(NS)": 0.11,
      "PGV(EW)": 0.14,
      "Int": 1,
      "PGA(SUM)": 1.4,
      "PGV(SUM)": 0.15,
      "City": "臺中市"
    },
    {
      "Stacode": "WWF",
      "Staname": "霧峰",
      "Stalon": 120.7,
      "Stalat": 24.04,
      "Dist": 86.3,
      "AZ": 101.28,
      "PGA(V)": 0.87,
      "PGA(NS)": 1.25,
      "PGA(EW)": 1.44,
      "PGV(V)": 0.08,
      "PGV(NS)": 0.18,
      "PGV(EW)": 0.2,
      "Int": 1,
      "PGA(SUM)": 1.46,
      "PGV(SUM)": 0.23,
      "City": "臺中市"
    },
    {
      "Stacode": "TCU",
      "Staname": "臺中市",
      "Stalon": 120.68,
      "Stalat": 24.15,
      "Dist": 90.58,
      "AZ": 108.19,
      "PGA(V)": 0.66,
      "PGA(NS)": 0.88,
      "PGA(EW)": 1.88,
      "PGV(V)": 0.11,
      "PGV(NS)": 0.17,
      "PGV(EW)": 0.18,
      "Int": 1,
      "PGA(SUM)": 1.89,
      "PGV(SUM)": 0.19,
      "City": "臺中市"
    },
    {
      "Stacode": "WDJ",
      "Staname": "大甲",
      "Stalon": 120.64,
      "Stalat": 24.35,
      "Dist": 103.66,
      "AZ": 119.26,
      "PGA(V)": 0.61,
      "PGA(NS)": 0.76,
      "PGA(EW)": 0.81,
      "PGV(V)": 0.08,
      "PGV(NS)": 0.13,
      "PGV(EW)": 0.13,
      "Int": 1,
      "PGA(SUM)": 0.82,
      "PGV(SUM)": 0.17,
      "City": "臺中市"
    },
    {
      "Stacode": "HSN1",
      "Staname": "新竹市",
      "Stalon": 121.02,
      "Stalat": 24.78,
      "Dist": 111.2,
      "AZ": 152.15,
      "PGA(V)": 0.73,
      "PGA(NS)": 1.27,
      "PGA(EW)": 1.01,
      "PGV(V)": 0.09,
      "PGV(NS)": 0.12,
      "PGV(EW)": 0.14,
      "Int": 1,
      "PGA(SUM)": 1.3,
      "PGV(SUM)": 0.14,
      "City": "新竹市"
    },
    {
      "Stacode": "TWL",
      "Staname": "東山",
      "Stalon": 120.5,
      "Stalat": 23.26,
      "Dist": 125.91,
      "AZ": 56.62,
      "PGA(V)": 0.56,
      "PGA(NS)": 0.75,
      "PGA(EW)": 1.02,
      "PGV(V)": 0.09,
      "PGV(NS)": 0.1,
      "PGV(EW)": 0.16,
      "Int": 1,
      "PGA(SUM)": 1.15,
      "PGV(SUM)": 0.18,
      "City": "臺南市"
    },
    {
      "Stacode": "TAP",
      "Staname": "臺北市",
      "Stalon": 121.51,
      "Stalat": 25.04,
      "Dist": 127.09,
      "AZ": 179.26,
      "PGA(V)": 0.87,
      "PGA(NS)": 1.17,
      "PGA(EW)": 1.04,
      "PGV(V)": 0.06,
      "PGV(NS)": 0.11,
      "PGV(EW)": 0.08,
      "Int": 1,
      "PGA(SUM)": 1.33,
      "PGV(SUM)": 0.12,
      "City": "臺北市"
    },
    {
      "Stacode": "NHY",
      "Staname": "信義區",
      "Stalon": 121.57,
      "Stalat": 25.04,
      "Dist": 127.32,
      "AZ": 181.79,
      "PGA(V)": 2.23,
      "PGA(NS)": 1.33,
      "PGA(EW)": 2.02,
      "PGV(V)": 0.08,
      "PGV(NS)": 0.11,
      "PGV(EW)": 0.09,
      "Int": 1,
      "PGA(SUM)": 1.2,
      "PGV(SUM)": 0.11,
      "City": "臺北市"
    },
    {
      "Stacode": "SSH",
      "Staname": "善化",
      "Stalon": 120.29,
      "Stalat": 23.14,
      "Dist": 151.87,
      "AZ": 56.63,
      "PGA(V)": 0.38,
      "PGA(NS)": 1.19,
      "PGA(EW)": 1.22,
      "PGV(V)": 0.08,
      "PGV(NS)": 0.23,
      "PGV(EW)": 0.21,
      "Int": 1,
      "PGA(SUM)": 1.36,
      "PGV(SUM)": 0.24,
      "City": "臺南市"
    },
    {
      "Stacode": "SHH",
      "Staname": "新化",
      "Stalon": 120.35,
      "Stalat": 23.02,
      "Dist": 154.42,
      "AZ": 51.45,
      "PGA(V)": 0.54,
      "PGA(NS)": 1.25,
      "PGA(EW)": 1.42,
      "PGV(V)": 0.08,
      "PGV(NS)": 0.21,
      "PGV(EW)": 0.22,
      "Int": 1,
      "PGA(SUM)": 1.69,
      "PGV(SUM)": 0.31,
      "City": "臺南市"
    },
    {
      "Stacode": "SCL",
      "Staname": "佳里",
      "Stalon": 120.2,
      "Stalat": 23.17,
      "Dist": 157.15,
      "AZ": 59.66,
      "PGA(V)": 0.9,
      "PGA(NS)": 1.02,
      "PGA(EW)": 0.99,
      "PGV(V)": 0.04,
      "PGV(NS)": 0.15,
      "PGV(EW)": 0.12,
      "Int": 1,
      "PGA(SUM)": 1.05,
      "PGV(SUM)": 0.16,
      "City": "臺南市"
    },
    {
      "Stacode": "TAI1",
      "Staname": "永康",
      "Stalon": 120.24,
      "Stalat": 23.04,
      "Dist": 162.4,
      "AZ": 54.46,
      "PGA(V)": 0.3,
      "PGA(NS)": 1.08,
      "PGA(EW)": 0.88,
      "PGV(V)": 0.03,
      "PGV(NS)": 0.19,
      "PGV(EW)": 0.16,
      "Int": 1,
      "PGA(SUM)": 1.25,
      "PGV(SUM)": 0.19,
      "City": "臺南市"
    },
    {
      "Stacode": "SCK",
      "Staname": "七股",
      "Stalon": 120.09,
      "Stalat": 23.15,
      "Dist": 168.85,
      "AZ": 60.81,
      "PGA(V)": 0.29,
      "PGA(NS)": 1.01,
      "PGA(EW)": 0.96,
      "PGV(V)": 0.03,
      "PGV(NS)": 0.11,
      "PGV(EW)": 0.14,
      "Int": 1,
      "PGA(SUM)": 0.99,
      "PGV(SUM)": 0.15,
      "City": "臺南市"
    }
  ]
}