{
  "earthquake_id": "173",
  "timestamp": "2022-11-20T09:49:41",
  "latitude": 24.65,
  "longitude": 121.95,
  "depth_km": 68.9,
  "magnitude": 5.1,
  "stations": [
    {
      "Stacode": "TWA",
      "Staname": "木柵",
      "Stalon": 121.59,
      "Stalat": 24.98,
      "Dist": 50.97,
      "BAZ": 134.67,
      "PGA(V)": 1.45,
      "PGA(NS)": 2.77,
      "PGA(EW)": 1.9,
      "PGV(V)": 0.09,
      "PGV(NS)": 0.16,
      "PGV(EW)": 0.11,
      "Int": 2,
      "PGA(SUM)": 2.74,
      "PGV(SUM)": 0.17,
      "City": "臺北市"
    },
    {
      "Stacode": "TAP",
      "Staname": "臺北市",
      "Stalon": 121.51,
      "Stalat": 25.04,
      "Dist": 61.27,
      "BAZ": 133.87,
      "PGA(V)": 3.82,
      "PGA(NS)": 6.09,
      "PGA(EW)": 5.4,
      "PGV(V)": 0.14,
      "PGV(NS)": 0.27,
      "PGV(EW)": 0.28,
      "Int": 2,
      "PGA(SUM)": 7.24,
      "PGV(SUM)": 0.32,
      "City": "臺北市"
    },
    {
      "Stacode": "FUSS",
      "Staname": "梨山",
      "Stalon": 121.24,
      "Stalat": 24.25,
      "Dist": 84.66,
      "BAZ": 57.85,
      "PGA(V)": 0.68,
      "PGA(NS)": 1.44,
      "PGA(EW)": 1.25,
      "PGV(V)": 0.02,
      "PGV(NS)": 0.05,
      "PGV(EW)": 0.05,
      "Int": 1,
      "PGA(SUM)": 1.8,
      "PGV(SUM)": 0.06,
      "City": "臺中市"
    },
    {
      "Stacode": "TWT",
      "Staname": "德基",
      "Stalon": 121.16,
      "Stalat": 24.25,
      "Dist": 91.69,
      "BAZ": 60.72,
      "PGA(V)": 1.39,
      "PGA(NS)": 2.84,
      "PGA(EW)": 1.94,
      "PGV(V)": 0.06,
      "PGV(NS)": 0.1,
      "PGV(EW)": 0.1,
      "Int": 2,
      "PGA(SUM)": 2.98,
      "PGV(SUM)": 0.12,
      "City": "臺中市"
    },
    {
      "Stacode": "HSN1",
      "Staname": "新竹市",
      "Stalon": 121.02,
      "Stalat": 24.78,
      "Dist": 95.37,
      "BAZ": 98.26,
      "PGA(V)": 1.34,
      "PGA(NS)": 3.56,
      "PGA(EW)": 2.75,
      "PGV(V)": 0.05,
      "PGV(NS)": 0.13,
      "PGV(EW)": 0.17,
      "Int": 2,
      "PGA(SUM)": 3.33,
      "PGV(SUM)": 0.17,
      "City": "新竹市"
    }
  ]
}