{
  "earthquake_id": "106",
  "timestamp": "2024-04-04T03:07:26",
  "latitude": 23.95,
  "longitude": 121.65,
  "depth_km": 41.4,
  "magnitude": 4.6,
  "stations": [
    {
      "Stacode": "FUSS",
      "Staname": "梨山",
      "Stalon": 121.24,
      "Stalat": 24.25,
      "Dist": 52.84,
      "BAZ": 129.18,
      "PGA(V)": 1.36,
      "PGA(NS)": 2.6,
      "PGA(EW)": 1.6,
      "PGV(V)": 0.04,
      "PGV(NS)": 0.07,
      "PGV(EW)": 0.06,
      "Int": 2,
      "PGA(SUM)": 2.84,
      "PGV(SUM)": 0.09,
      "City": "臺中市"
    },
    {
      "Stacode": "TWT",
      "Staname": "德基",
      "Stalon": 121.16,
      "Stalat": 24.25,
      "Dist": 59.65,
      "BAZ": 124.28,
      "PGA(V)": 2.18,
      "PGA(NS)": 3.83,
      "PGA(EW)": 2.3,
      "PGV(V)": 0.05,
      "PGV(NS)": 0.09,
      "PGV(EW)": 0.06,
      "Int": 2,
      "PGA(SUM)": 3.63,
      "PGV(SUM)": 0.1,
      "City": "臺中市"
    },
    {
      "Stacode": "B219",
      "Staname": "霧峰",
      "Stalon": 120.7,
      "Stalat": 24.04,
      "Dist": 96.95,
      "BAZ": 96.29,
      "PGA(V)": 0.82,
      "PGA(NS)": 2.05,
      "PGA(EW)": 1.67,
      "PGV(V)": 0.03,
      "PGV(NS)": 0.04,
      "PGV(EW)": 0.06,
      "Int": 1,
      "PGA(SUM)": 1.64,
      "PGV(SUM)": 0.06,
      "City": "臺中市"
    }
  ]
}